slicer_package_manager_client/__init__.py
slicer_package_manager_client/__main__.py
slicer_package_manager_client/cli.py
slicer_package_manager_client/_vendor/__init__.py
slicer_package_manager_client/_vendor/bson/__init__.py
slicer_package_manager_client/_vendor/bson/errors.py
slicer_package_manager_client/_vendor/bson/objectid.py
slicer_package_manager_client/_vendor/bson/py3compat.py
slicer_package_manager_client/_vendor/bson/tz_util.py
slicer_package_manager_client-0.9.0.dist-info/METADATA
slicer_package_manager_client-0.9.0.dist-info/WHEEL
slicer_package_manager_client-0.9.0.dist-info/entry_points.txt
slicer_package_manager_client-0.9.0.dist-info/top_level.txt
slicer_package_manager_client-0.9.0.dist-info/RECORD
