Metadata-Version: 2.1
Name: slicer-package-manager-client
Version: 0.9.0
Summary: Python client for interacting with the Slicer package manager endpoint.
Author-email: Pierre Assemat <pierre.assemat@kitware.com>, Jean-Christophe Fillion-Robin <jchris.fillionr@kitware.com>
Maintainer-email: Jean-Christophe Fillion-Robin <jchris.fillionr@kitware.com>
Project-URL: Documentation, https://slicer-package-manager.readthedocs.io/en/latest/commands_shell.html#slicer-package-manager-client
Project-URL: Source, https://github.com/girder/slicer_package_manager/tree/main/python_client
Classifier: Environment :: Console
Classifier: License :: OSI Approved :: Apache Software License
Classifier: Operating System :: OS Independent
Classifier: Programming Language :: Python :: 3
Requires-Python: >=3.7
Requires-Dist: click >=6.7
Requires-Dist: girder-client ~=3.1.20
Requires-Dist: tabulate
Provides-Extra: test
Requires-Dist: pytest ; extra == 'test'
Requires-Dist: pytest-vcr ; extra == 'test'
Requires-Dist: pytest-girder ~=3.1.20 ; extra == 'test'
